typtyp/__init__.py
typtyp/excs.py
typtyp/py.typed
typtyp/type_info.py
typtyp/typescript.py
typtyp/world.py
typtyp-0.1.0.dist-info/METADATA
typtyp-0.1.0.dist-info/WHEEL
typtyp-0.1.0.dist-info/licenses/LICENSE
typtyp-0.1.0.dist-info/RECORD
