Metadata-Version: 2.4
Name: typtyp
Version: 0.1.0
Summary: Convert Python types to TypeScript
Author-email: Aarni Koskela <akx@iki.fi>
License-Expression: MIT
License-File: LICENSE
Requires-Python: >=3.11
Provides-Extra: pydantic
Requires-Dist: pydantic>=2.0; extra == 'pydantic'
